job_queue_lambda/__init__.py
job_queue_lambda/__main__.py
job_queue_lambda/cluster.py
job_queue_lambda/config.py
job_queue_lambda/connector.py
job_queue_lambda/job_queue.py
job_queue_lambda/main.py
job_queue_lambda/server.py
job_queue_lambda/util.py
job_queue_lambda-0.0.3.dist-info/LICENSE
job_queue_lambda-0.0.3.dist-info/METADATA
job_queue_lambda-0.0.3.dist-info/WHEEL
job_queue_lambda-0.0.3.dist-info/entry_points.txt
job_queue_lambda-0.0.3.dist-info/RECORD
