Metadata-Version: 2.1
Name: job-queue-lambda
Version: 0.0.3
Summary: 
License: MIT
Author: weihong.xu
Author-email: xuweihong.cn@gmail.com
Requires-Python: >=3.9,<4.0
Classifier: License :: OSI Approved :: MIT License
Classifier: Programming Language :: Python :: 3
Classifier: Programming Language :: Python :: 3.9
Classifier: Programming Language :: Python :: 3.10
Classifier: Programming Language :: Python :: 3.11
Classifier: Programming Language :: Python :: 3.12
Requires-Dist: aiohttp (>=3.11.11,<4.0.0)
Requires-Dist: aiohttp-socks (==0.10.1)
Requires-Dist: asyncssh (>=2.19.0,<3.0.0)
Requires-Dist: fire (>=0.7.0,<0.8.0)
Requires-Dist: pydantic (>=2.10.5,<3.0.0)
Requires-Dist: pyyaml (>=6.0.2,<7.0.0)
